zini.py
zini-1.1.0.dist-info/DESCRIPTION.rst
zini-1.1.0.dist-info/METADATA
zini-1.1.0.dist-info/RECORD
zini-1.1.0.dist-info/WHEEL
zini-1.1.0.dist-info/metadata.json
zini-1.1.0.dist-info/top_level.txt
