Metadata-Version: 2.0
Name: zini
Version: 1.1.0
Summary: INI-files parser with schemes and types
Home-page: https://github.com/zzzsochi/zini
Author: Alexander Zelenyak
Author-email: zzz.sochi@gmail.com
License: UNKNOWN
Keywords: ini,settings,config,configure,configuration
Platform: UNKNOWN
Classifier: License :: OSI Approved :: BSD License
Classifier: Operating System :: POSIX
Classifier: Programming Language :: Python :: 3.3
Classifier: Programming Language :: Python :: 3.4
Classifier: Programming Language :: Python :: 3.5
Requires-Dist: python-dateutil
